Workbook

Sheet Cover
A1: Cover
A2: PT TAPGO LION INDONESIA | TapGo Master Blueprint 2026-2035
A4: Company | B4: PT TAPGO LION INDONESIA
A5: Brand | B5: TapGo
A6: Scenario model | B6: Editable assumptions
A8: Dokumen ini merupakan rencana strategis dan model keuangan internal. Proyeksi, valuasi, target, dan estimasi di dalamnya didasarkan pada asumsi yang dapat berubah. Dokumen ini bukan penawaran efek, jaminan keuntungan, audit keuangan, atau appraisal independen.

Sheet Instructions
A1: Instructions
A2: PT TAPGO LION INDONESIA | TapGo Master Blueprint 2026-2035
A4: 1. Change scenario in Scenario Selector!B4.
A5: 2. Edit blue cells in Assumptions.
A6: 3. Review Checks sheet for PASS/FAIL.
A7: 4. This workbook is illustrative and must be updated with actual launch data.

Sheet Assumptions
A1: Assumptions
A2: PT TAPGO LION INDONESIA | TapGo Master Blueprint 2026-2035
A3: Input | B3: Value | C3: Notes
A4: Scenario | B4: Base | C4: Editable
A5: Initial Investment Baseline | B5: 800000000 | C5: Owner Confirmation Required
A6: Monthly Operating Budget | B6: 159500000 | C6: Owner Confirmation Required
A7: Emergency Reserve Months | B7: 2 | C7: Editable
A8: Payment Gateway Fee Rate | B8: 0.02 | C8: Editable
A9: Tax Rate | B9: 0.11 | C9: Editable
A10: Sponsor Bonus Rate | B10: 0.08 | C10: Editable
A11: Level Bonus Max Rate | B11: 0.23 | C11: Editable
A12: Reward Provision Rate | B12: 0.02 | C12: Editable
A13: Operational Allocation Rate | B13: 0.1 | C13: Editable
A14: Silver Price | B14: 500000 | C14: Editable
A15: Gold Price | B15: 3000000 | C15: Editable
A16: Platinum Price | B16: 5500000 | C16: Editable
... A28: Funding Seed High | B28: 5000000000 | C28: Editable

Sheet Scenario Selector
A1: Scenario Selector
A2: PT TAPGO LION INDONESIA | TapGo Master Blueprint 2026-2035
A3: Scenario | B3: Growth Multiplier | C3: Cost Multiplier | D3: CAC Multiplier
A4: Conservative | B4: 0.65 | C4: 0.9 | D4: 0.9
A5: Base | B5: 1 | C5: 1 | D5: 1
A6: Selected | B6: Base | C6: 1.25 | D6: 1.2

Sheet Membership Economics
A1: Membership Economics
A2: Silver | B2: ='Assumptions'!B11 | C2: ='Assumptions'!B14 | D2: ='Assumptions'!B17 | E2: =B2*'Assumptions'!B5 | F2: =B2*'Assumptions'!B7 | G2: =B2*'Assumptions'!B8 | H2: =B2*'Assumptions'!B9 | I2: =B2*'Assumptions'!B6 | J2: =B2*'Assumptions'!B10 | K2: =B2-SUM(C2:J2)
A3: Gold | B3: ='Assumptions'!B12 | C3: ='Assumptions'!B15 | D3: ='Assumptions'!B18 | E3: =B3*'Assumptions'!B5 | F3: =B3*'Assumptions'!B7 | G3: =B3*'Assumptions'!B8 | H3: =B3*'Assumptions'!B9 | I3: =B3*'Assumptions'!B6 | J3: =B3*'Assumptions'!B10 | K3: =B3-SUM(C3:J3)
A4: Platinum | B4: ='Assumptions'!B13 | C4: ='Assumptions'!B16 | D4: ='Assumptions'!B19 | E4: =B4*'Assumptions'!B5 | F4: =B4*'Assumptions'!B7 | G4: =B4*'Assumptions'!B8 | H4: =B4*'Assumptions'!B9 | I4: =B4*'Assumptions'!B6 | J4: =B4*'Assumptions'!B10 | K4: =B4-SUM(C4:J4)

Sheet Bonus Liability
A1: Bonus Liability
A2: Low | B2: 0.25 | C2: ='Revenue Build'!F5 | D2: =B2*C2
A3: Managed | B3: 0.4 | C3: ='Revenue Build'!F5 | D3: =B3*C3
A4: Stress | B4: 0.6 | C4: ='Revenue Build'!F5 | D4: =B4*C4
A5: Concentration | B5: 0.75 | C5: ='Revenue Build'!F5 | D5: =B5*C5

Sheet User Growth
A1: User Growth
A2: PT TAPGO LION INDONESIA | TapGo Master Blueprint 2026-2035
A3: Metric | B3: 2026 | C3: 2027 | D3: 2028 | E3: 2029 | F3: 2030
A4: Registered Users | B4: 10000 | C4: =B2*5 | D4: =C2*2 | E4: =D2*1.5 | F4: =E2*1.4
A5: Active Users | B5: =B2*45% | C5: =C2*50% | D5: =D2*55% | E5: =E2*58% | F5: =F2*60%
A6: Paid Members | B6: =B3*18% | C6: =C3*20% | D6: =D3*22% | E6: =E3*24% | F6: =F3*25%

Sheet Merchant Growth
A1: Merchant Growth
A2: PT TAPGO LION INDONESIA | TapGo Master Blueprint 2026-2035
A3: Metric | B3: 2026 | C3: 2027 | D3: 2028 | E3: 2029 | F3: 2030
A4: Registered Merchants | B4: 250 | C4: 1500 | D4: 5000 | E4: 12000 | F4: 20000
A5: Active Merchants | B5: =B2*45% | C5: =C2*55% | D5: =D2*60% | E5: =E2*65% | F5: =F2*70%

Sheet Revenue Build
A1: Revenue Build
A2: PT TAPGO LION INDONESIA | TapGo Master Blueprint 2026-2035
A3: Metric | B3: 2026 | C3: 2027 | D3: 2028 | E3: 2029 | F3: 2030
A4: Paid Members | B4: ='User Growth'!B4 | C4: ='User Growth'!C4 | D4: ='User Growth'!D4 | E4: ='User Growth'!E4 | F4: ='User Growth'!F4
A5: Avg Membership Revenue | B5: 800000 | C5: 900000 | D5: 1000000 | E5: 1050000 | F5: 1100000
A6: Membership Revenue | B6: =B2*B3 | C6: =C2*C3 | D6: =D2*D3 | E6: =E2*E3 | F6: =F2*F3
A7: Merchant Revenue | B7: ='Merchant Growth'!B3*'Assumptions'!B22*12 | C7: ='Merchant Growth'!C3*'Assumptions'!B22*12 | D7: ='Merchant Growth'!D3*'Assumptions'!B22*12 | E7: ='Merchant Growth'!E3*'Assumptions'!B22*12 | F7: ='Merchant Growth'!F3*'Assumptions'!B22*12
A8: Total Revenue | B8: =B4+B5 | C8: =C4+C5 | D8: =D4+D5 | E8: =E4+E5 | F8: =F4+F5

Sheet Variable Cost
A1: Variable Cost
A2: PT TAPGO LION INDONESIA | TapGo Master Blueprint 2026-2035
A3: Metric | B3: 2026 | C3: 2027 | D3: 2028 | E3: 2029 | F3: 2030
A4: Gateway Cost | B4: ='Revenue Build'!B6*'Assumptions'!B5 | C4: ='Revenue Build'!C6*'Assumptions'!B5 | D4: ='Revenue Build'!D6*'Assumptions'!B5 | E4: ='Revenue Build'!E6*'Assumptions'!B5 | F4: ='Revenue Build'!F6*'Assumptions'!B5
A5: Bonus/Reward Provision | B5: ='Revenue Build'!B4*35% | C5: ='Revenue Build'!C4*35% | D5: ='Revenue Build'!D4*35% | E5: ='Revenue Build'!E4*35% | F5: ='Revenue Build'!F4*35%
A6: Other Variable Cost | B6: ='Revenue Build'!B6*8% | C6: ='Revenue Build'!C6*8% | D6: ='Revenue Build'!D6*8% | E6: ='Revenue Build'!E6*8% | F6: ='Revenue Build'!F6*8%
A7: Total Variable Cost | B7: =SUM(B2:B4) | C7: =SUM(C2:C4) | D7: =SUM(D2:D4) | E7: =SUM(E2:E4) | F7: =SUM(F2:F4)

Sheet Fixed Cost
A1: Fixed Cost
A2: PT TAPGO LION INDONESIA | TapGo Master Blueprint 2026-2035
A3: Metric | B3: 2026 | C3: 2027 | D3: 2028 | E3: 2029 | F3: 2030
A4: Annual Fixed Cost | B4: ='Assumptions'!B3*12 | C4: =B2*1.25 | D4: =C2*1.25 | E4: =D2*1.22 | F4: =E2*1.18

Sheet Headcount
A1: Headcount
A2: PT TAPGO LION INDONESIA | TapGo Master Blueprint 2026-2035
A3: Category | B3: 2026 | C3: 2027 | D3: 2028 | E3: 2029 | F3: 2030
A4: Core Team | B4: 8 | C4: 14 | D4: 24 | E4: 38 | F4: 55
A5: Regional/Ops | B5: 3 | C5: 10 | D5: 25 | E5: 55 | F5: 90

Sheet Capex
A1: Capex
A2: PT TAPGO LION INDONESIA | TapGo Master Blueprint 2026-2035
A3: Category | B3: 2026 | C3: 2027 | D3: 2028 | E3: 2029 | F3: 2030
A4: Product & Software | B4: 350000000 | C4: 250000000 | D4: 300000000 | E4: 350000000 | F4: 400000000
A5: Equipment | B5: 75000000 | C5: 100000000 | D5: 150000000 | E5: 200000000 | F5: 250000000

Sheet P&L Monthly
A1: P&L Monthly
A2: PT TAPGO LION INDONESIA | TapGo Master Blueprint 2026-2035
A3: Month | B3: Revenue | C3: Opex | D3: EBITDA
A4: Month 1 | B4: ='Revenue Build'!B6/12*POWER(1.03,0) | C4: ='Assumptions'!B3 | D4: =B2-C2
A5: Month 2 | B5: ='Revenue Build'!B6/12*POWER(1.03,1) | C5: ='Assumptions'!B3 | D5: =B3-C3
A6: Month 3 | B6: ='Revenue Build'!B6/12*POWER(1.03,2) | C6: ='Assumptions'!B3 | D6: =B4-C4
A7: Month 4 | B7: ='Revenue Build'!B6/12*POWER(1.03,3) | C7: ='Assumptions'!B3 | D7: =B5-C5
A8: Month 5 | B8: ='Revenue Build'!B6/12*POWER(1.03,4) | C8: ='Assumptions'!B3 | D8: =B6-C6
A9: Month 6 | B9: ='Revenue Build'!B6/12*POWER(1.03,5) | C9: ='Assumptions'!B3 | D9: =B7-C7
A10: Month 7 | B10: ='Revenue Build'!B6/12*POWER(1.03,6) | C10: ='Assumptions'!B3 | D10: =B8-C8
A11: Month 8 | B11: ='Revenue Build'!B6/12*POWER(1.03,7) | C11: ='Assumptions'!B3 | D11: =B9-C9
A12: Month 9 | B12: ='Revenue Build'!B6/12*POWER(1.03,8) | C12: ='Assumptions'!B3 | D12: =B10-C10
A13: Month 10 | B13: ='Revenue Build'!B6/12*POWER(1.03,9) | C13: ='Assumptions'!B3 | D13: =B11-C11
A14: Month 11 | B14: ='Revenue Build'!B6/12*POWER(1.03,10) | C14: ='Assumptions'!B3 | D14: =B12-C12
A15: Month 12 | B15: ='Revenue Build'!B6/12*POWER(1.03,11) | C15: ='Assumptions'!B3 | D15: =B13-C13
A16: Month 13 | B16: ='Revenue Build'!B6/12*POWER(1.03,12) | C16: ='Assumptions'!B3 | D16: =B14-C14
A17: Month 14 | B17: ='Revenue Build'!B6/12*POWER(1.03,13) | C17: ='Assumptions'!B3 | D17: =B15-C15
A18: Month 15 | B18: ='Revenue Build'!B6/12*POWER(1.03,14) | C18: ='Assumptions'!B3 | D18: =B16-C16
A19: Month 16 | B19: ='Revenue Build'!B6/12*POWER(1.03,15) | C19: ='Assumptions'!B3 | D19: =B17-C17
A20: Month 17 | B20: ='Revenue Build'!B6/12*POWER(1.03,16) | C20: ='Assumptions'!B3 | D20: =B18-C18
A21: Month 18 | B21: ='Revenue Build'!B6/12*POWER(1.03,17) | C21: ='Assumptions'!B3 | D21: =B19-C19
A22: Month 19 | B22: ='Revenue Build'!B6/12*POWER(1.03,18) | C22: ='Assumptions'!B3 | D22: =B20-C20
A23: Month 20 | B23: ='Revenue Build'!B6/12*POWER(1.03,19) | C23: ='Assumptions'!B3 | D23: =B21-C21
A24: Month 21 | B24: ='Revenue Build'!B6/12*POWER(1.03,20) | C24: ='Assumptions'!B3 | D24: =B22-C22
A25: Month 22 | B25: ='Revenue Build'!B6/12*POWER(1.03,21) | C25: ='Assumptions'!B3 | D25: =B23-C23
A26: Month 23 | B26: ='Revenue Build'!B6/12*POWER(1.03,22) | C26: ='Assumptions'!B3 | D26: =B24-C24
A27: Month 24 | B27: ='Revenue Build'!B6/12*POWER(1.03,23) | C27: ='Assumptions'!B3 | D27: =B25-C25

Sheet P&L Annual
A1: P&L Annual
A2: PT TAPGO LION INDONESIA | TapGo Master Blueprint 2026-2035
A3: Metric | B3: 2026 | C3: 2027 | D3: 2028 | E3: 2029 | F3: 2030
A4: Revenue | B4: ='Revenue Build'!B6 | C4: ='Revenue Build'!C6 | D4: ='Revenue Build'!D6 | E4: ='Revenue Build'!E6 | F4: ='Revenue Build'!F6
A5: Cost of Revenue | B5: ='Variable Cost'!B5 | C5: ='Variable Cost'!C5 | D5: ='Variable Cost'!D5 | E5: ='Variable Cost'!E5 | F5: ='Variable Cost'!F5
A6: Gross Profit | B6: =B2-B3 | C6: =C2-C3 | D6: =D2-D3 | E6: =E2-E3 | F6: =F2-F3
A7: Operating Expense | B7: ='Fixed Cost'!B2 | C7: ='Fixed Cost'!C2 | D7: ='Fixed Cost'!D2 | E7: ='Fixed Cost'!E2 | F7: ='Fixed Cost'!F2
A8: EBITDA | B8: =B4-B5 | C8: =C4-C5 | D8: =D4-D5 | E8: =E4-E5 | F8: =F4-F5
A9: Tax | B9: =MAX(0,B6*'Assumptions'!B6) | C9: =MAX(0,C6*'Assumptions'!B6) | D9: =MAX(0,D6*'Assumptions'!B6) | E9: =MAX(0,E6*'Assumptions'!B6) | F9: =MAX(0,F6*'Assumptions'!B6)
A10: Net Profit | B10: =B6-B7 | C10: =C6-C7 | D10: =D6-D7 | E10: =E6-E7 | F10: =F6-F7

Sheet Balance Sheet
A1: Balance Sheet
A2: PT TAPGO LION INDONESIA | TapGo Master Blueprint 2026-2035
A3: Metric | B3: 2026 | C3: 2027 | D3: 2028 | E3: 2029 | F3: 2030
A4: Cash | B4: ='Cash Flow'!B5 | C4: ='Cash Flow'!C5 | D4: ='Cash Flow'!D5 | E4: ='Cash Flow'!E5 | F4: ='Cash Flow'!F5
A5: Fixed Assets | B5: 800000000 | C5: 900000000 | D5: 1000000000 | E5: 1100000000 | F5: 1200000000
A6: Total Assets | B6: =B2+B3 | C6: =C2+C3 | D6: =D2+D3 | E6: =E2+E3 | F6: =F2+F3
A7: Liabilities | B7: 300000000 | C7: 350000000 | D7: 450000000 | E7: 550000000 | F7: 650000000
A8: Equity | B8: =B4-B5 | C8: =C4-C5 | D8: =D4-D5 | E8: =E4-E5 | F8: =F4-F5
A9: Check | B9: =B4-B5-B6 | C9: =C4-C5-C6 | D9: =D4-D5-D6 | E9: =E4-E5-E6 | F9: =F4-F5-F6

Sheet Cash Flow
A1: Cash Flow
A2: PT TAPGO LION INDONESIA | TapGo Master Blueprint 2026-2035
A3: Metric | B3: 2026 | C3: 2027 | D3: 2028 | E3: 2029 | F3: 2030
A4: Opening Cash | B4: ='Assumptions'!B23 | C4: =B5 | D4: =C5 | E4: =D5 | F4: =E5
A5: Operating Cash Flow | B5: ='P&L Annual'!B8 | C5: ='P&L Annual'!C8 | D5: ='P&L Annual'!D8 | E5: ='P&L Annual'!E8 | F5: ='P&L Annual'!F8
A6: Capex | B6: =-'Assumptions'!B2 | C6: =-250000000 | D6: =-300000000 | E6: =-350000000 | F6: =-400000000
A7: Financing Cash Flow | B7: 0 | C7: 0 | D7: 0 | E7: 0 | F7: 0
A8: Ending Cash | B8: =SUM(B2:B4) | C8: =SUM(C2:C4) | D8: =SUM(D2:D4) | E8: =SUM(E2:E4) | F8: =SUM(F2:F4)

Sheet Working Capital
A1: Working Capital
A2: 6 months | B2: ='Assumptions'!B3*6 | C2: =B2
A3: 12 months | B3: ='Assumptions'!B3*12 | C3: =B3
A4: 18 months | B4: ='Assumptions'!B3*18 | C4: =B4

Sheet Break-Even
A1: Break-Even
A2: PT TAPGO LION INDONESIA | TapGo Master Blueprint 2026-2035
A3: Metric | B3: Formula | C3: Base Result
A4: Annual Fixed Cost | B4: ='Fixed Cost'!B2 | C4: =B2
A5: Avg Contribution per Paid Member | B5: ='Membership Economics'!K2 | C5: =B3
A6: Break-Even Paid Members | B6: =ROUNDUP(B2/B3,0) | C6: =B4
A7: Estimated Break-Even Year | B7: 2029 if EBITDA turns positive in base scenario | C7: 2029

Sheet Unit Economics
A1: Unit Economics
A2: PT TAPGO LION INDONESIA | TapGo Master Blueprint 2026-2035
A3: Metric | B3: Formula / Assumption | C3: Base
A4: CAC | B4: ='Assumptions'!B20 | C4: ='Assumptions'!B20
A5: ARPU Monthly | B5: ='Assumptions'!B21 | C5: ='Assumptions'!B21
A6: Gross Margin | B6: ='P&L Annual'!B4/'P&L Annual'!B2 | C6: ='P&L Annual'!B4/'P&L Annual'!B2
A7: Payback Months | B7: =CAC/ARPU | C7: =C2/C3

Sheet Funding
A1: Funding
A2: PT TAPGO LION INDONESIA | TapGo Master Blueprint 2026-2035
A3: Use of Funds | B3: Amount
A4: Product Development | B4: 350000000
A5: Infrastructure Setup | B5: 75000000
A6: Equipment | B6: 75000000
A7: Branding | B7: 30000000
A8: Legal & Compliance | B8: 40000000
A9: Initial Marketing | B9: 100000000
A10: Office Setup | B10: 50000000
A11: Contingency | B11: 80000000
A12: 12 Month Working Capital | B12: ='Working Capital'!C3
A13: Total Baseline Requirement | B13: =SUM(B2:B10)

Sheet Valuation
A1: Valuation
A2: PT TAPGO LION INDONESIA | TapGo Master Blueprint 2026-2035
A3: Method | B3: Conservative | C3: Base | D3: Upside | E3: Disclaimer
A4: Revenue Multiple | B4: ='Revenue Build'!D6*1.0 | C4: ='Revenue Build'!D6*1.8 | D4: ='Revenue Build'!D6*3.0 | E4: Illustrative only
A5: EBITDA Multiple | B5: =MAX(0,'P&L Annual'!D6*5) | C5: =MAX(0,'P&L Annual'!E6*7) | D5: =MAX(0,'P&L Annual'!F6*9) | E5: Not appraisal
A6: VC Method | B6: 2000000000 | C6: 5000000000 | D6: 12000000000 | E6: Highly assumption sensitive

Sheet Sensitivity
A1: Sensitivity
A2: PT TAPGO LION INDONESIA | TapGo Master Blueprint 2026-2035
A3: Driver | B3: Low | C3: Base | D3: High
A4: Bonus Payout | B4: 0.25 | C4: 0.4 | D4: 0.6
A5: CAC | B5: 45000 | C5: 65000 | D5: 95000
A6: Paid Conversion | B6: 0.12 | C6: 0.2 | D6: 0.28
A7: Fixed Cost Multiplier | B7: 0.85 | C7: 1 | D7: 1.25

Sheet KPI Dashboard
A1: KPI Dashboard
A2: PT TAPGO LION INDONESIA | TapGo Master Blueprint 2026-2035
A3: KPI Category | B3: Metric | C3: Target Use
A4: Member | B4: Registered / Active / Paid / Churn / Retention | C4: Growth quality
A5: Merchant | B5: Registered / Active / GMV / Revenue | C5: Ecosystem scale
A6: Payment | B6: Success rate / Webhook success / Refund / Chargeback | C6: Reliability
A7: Finance | B7: Revenue / Gross margin / EBITDA / Burn / Runway | C7: Capital discipline
A8: Operations | B8: Ticket SLA / NPS / Uptime / Fraud rate | C8: Service quality

Sheet Checks
A1: Checks
A2: PT TAPGO LION INDONESIA | TapGo Master Blueprint 2026-2035
A3: Check | B3: Formula | C3: Status
A4: Balance Sheet balances 2030 | B4: ='Balance Sheet'!F7 | C4: =IF(ABS(B2)<1,"PASS","FAIL")
A5: Ending cash is numeric | B5: ='Cash Flow'!F5 | C5: =IF(ISNUMBER(B3),"PASS","FAIL")
A6: Funding requirement positive | B6: ='Funding'!B11 | C6: =IF(B4>0,"PASS","FAIL")
